{
  "itemEffects": [
    {
      "itemId": "the_vault:jade_apple",
      "absorption": true,
      "absorptionAmount": 0.0,
      "effects": [
        {
          "effectId": "minecraft:haste",
          "amplifier": 3,
          "duration": 2400,
          "ambient": false,
          "showParticles": false,
          "showIcon": true
        }
      ],
      "type": "basic"
    },
    {
      "itemId": "the_vault:cobalt_apple",
      "absorption": true,
      "absorptionAmount": 0.0,
      "effects": [
        {
          "effectId": "minecraft:fire_resistance",
          "amplifier": 1,
          "duration": 2400,
          "ambient": false,
          "showParticles": false,
          "showIcon": true
        },
        {
          "effectId": "botania:feather_feet",
          "amplifier": 1,
          "duration": 2400,
          "ambient": false,
          "showParticles": false,
          "showIcon": true
        }
      ],
      "type": "basic"
    },
    {
      "itemId": "the_vault:pixie_apple",
      "absorption": true,
      "absorptionAmount": 0.0,
      "effects": [
        {
          "effectId": "minecraft:slow_falling",
          "amplifier": 2,
          "duration": 2400,
          "ambient": false,
          "showParticles": false,
          "showIcon": true
        },
        {
          "effectId": "minecraft:jump_boost",
          "amplifier": 2,
          "duration": 2400,
          "ambient": false,
          "showParticles": false,
          "showIcon": true
        }
      ],
      "type": "basic"
    },
    {
      "itemId": "the_vault:candy_bar",
      "absorption": false,
      "absorptionAmount": 0.0,
      "effects": [
        {
          "effectId": "minecraft:speed",
          "amplifier": 5,
          "duration": 600,
          "ambient": false,
          "showParticles": false,
          "showIcon": true
        }
      ],
      "type": "basic"
    },
    {
      "itemId": "the_vault:power_bar",
      "absorption": false,
      "absorptionAmount": 0.0,
      "effects": [
        {
          "effectId": "minecraft:strength",
          "amplifier": 4,
          "duration": 600,
          "ambient": false,
          "showParticles": false,
          "showIcon": true
        }
      ],
      "type": "basic"
    },
    {
      "itemId": "the_vault:lucky_apple",
      "absorption": false,
      "absorptionAmount": 0.0,
      "effects": [
        {
          "effectId": "minecraft:luck",
          "amplifier": 1,
          "duration": 600,
          "ambient": false,
          "showParticles": false,
          "showIcon": true
        }
      ],
      "type": "powerup"
    },
    {
      "itemId": "the_vault:treasure_apple",
      "absorption": false,
      "absorptionAmount": 0.0,
      "effects": [
        {
          "effectId": "minecraft:luck",
          "amplifier": 5,
          "duration": 300,
          "ambient": false,
          "showParticles": false,
          "showIcon": true
        }
      ],
      "type": "powerup"
    },
    {
      "itemId": "the_vault:power_apple",
      "absorption": false,
      "absorptionAmount": 0.0,
      "effects": [
        {
          "effectId": "minecraft:strength",
          "amplifier": 2,
          "duration": 2400,
          "ambient": false,
          "showParticles": false,
          "showIcon": true
        }
      ],
      "type": "powerup"
    },
    {
      "itemId": "the_vault:ghost_apple",
      "absorption": false,
      "absorptionAmount": 0.0,
      "effects": [
        {
          "effectId": "the_vault:parry",
          "amplifier": 15,
          "duration": 2400,
          "ambient": false,
          "showParticles": false,
          "showIcon": true
        }
      ],
      "type": "powerup"
    },
    {
      "itemId": "the_vault:golem_apple",
      "absorption": false,
      "absorptionAmount": 0.0,
      "effects": [
        {
          "effectId": "the_vault:resistance",
          "amplifier": 10,
          "duration": 2400,
          "ambient": false,
          "showParticles": false,
          "showIcon": true
        }
      ],
      "type": "powerup"
    },
    {
      "itemId": "the_vault:sweet_apple",
      "absorption": false,
      "absorptionAmount": 0.0,
      "effects": [
        {
          "effectId": "minecraft:speed",
          "amplifier": 2,
          "duration": 2400,
          "ambient": false,
          "showParticles": false,
          "showIcon": true
        }
      ],
      "type": "powerup"
    },
    {
      "itemId": "the_vault:hearty_apple",
      "absorption": true,
      "absorptionAmount": 2.0,
      "effects": [],
      "type": "powerup"
    }
  ],
  "descriptions": {
    "the_vault:candy_bar": [
      "获得30秒 速度5"
    ],
    "the_vault:lucky_apple": [
      "Vault Powerup!",
      "获得30秒 幸运+1"
    ],
    "the_vault:cobalt_apple": [
      "获得2分钟 防火 + 摔落保护"
    ],
    "the_vault:golem_apple": [
      "Vault Powerup!",
      "获得2分钟 抗性提升+10%"
    ],
    "the_vault:power_bar": [
      "获得30秒 力量4"
    ],
    "the_vault:sweet_apple": [
      "Vault Powerup!",
      "获得2分钟 速度+2"
    ],
    "the_vault:power_apple": [
      "Vault Powerup!",
      "获得2分钟 力量+2"
    ],
    "the_vault:jade_apple": [
      "获得2分钟 急迫3"
    ],
    "the_vault:treasure_apple": [
      "Vault Powerup!",
      "获得15秒 幸运+5",
      " ",
      "Looter Boi reporting for looting?"

    ],
    "the_vault:pixie_apple": [
      "获得2分钟 速度5 + 跳跃2 + 缓降"
    ],
    "the_vault:ghost_apple": [
      "Vault Powerup!",
      "获得2分钟 格挡+15%"
    ],
    "the_vault:hearty_apple": [
      "获得 临时血量+1"
    ]
  }
}