{
  "tags": {
    "Defensive": {
      "tags": [
        "ModArmor",
        "ModKnockbackResistance",
        "ModCritHitMitigation",
        "focusArmor"
      ],
      "display": "\u9632\u5fa1",
      "color": 7973817,
      "weight": 0,
      "affixType": ["PREFIX"]
    },
    "ResDmg": {
      "tags": [
        "focusResistance",
        "focusDamage"
      ],
      "display": "\u6297\u6027/\u4f24\u5bb3",
      "color": 16760832,
      "weight": 0,
      "affixType": ["PREFIX"]
    },
    "Mana": {
      "tags": [
        "ModMana",
        "ModManaRegen"
      ],
      "display": "\u9b54\u529b",
      "color": 65535,
      "weight": 0,
      "affixType": []
    },
    "Looting": {
      "tags": [
        "ModItemRarity",
        "ModItemQuantity"
      ],
      "display": "\u6218\u5229\u54c1",
      "color": 15639054,
      "weight": 0,
      "affixType": ["SUFFIX"]
    },
    "Offensive": {
      "tags": [
        "ModOnHitAddition",
        "ModAttackDamage",
        "ModFatalStrikeDamage",
        "ModDamageIncrease",
        "ModTypedDamageIncrease",
        "ModFatalStrikeChance",
        "ModAttackSpeedPercent"
      ],
      "display": "\u653b\u51fb",
      "color": 12782347,
      "weight": 0,
      "affixType": ["PREFIX"]
    },
    "OnHit": {
      "tags": [
        "ModOnHitAddition"
      ],
      "display": "\u53d7\u51fb\u89e6\u53d1",
      "color": 16740864,
      "weight": 0,
      "affixType": ["PREFIX"]
    },
    "Resistance": {
      "tags": [
        "focusResistance"
      ],
      "display": "\u6297\u6027",
      "color": 16760832,
      "weight": 10,
      "affixType": ["PREFIX"]
    },
    "Lucky Hit": {
      "tags": [
        "focusLuckyHitChance"
      ],
      "display": "\u5e78\u8fd0\u4e00\u51fb",
      "color": 7206307,
      "weight": 10,
      "affixType": ["SUFFIX"]
    },
    "Slowness Cloud": {
      "tags": [
        "focusSlownessCloud"
      ],
      "display": "\u7f13\u6162\u6548\u679c\u4e91",
      "color": 7400423,
      "weight": 0,
      "affixType": ["SUFFIX"]
    },
    "Chilling Cloud": {
      "tags": [
        "focusChillingCloud"
      ],
      "display": "\u971c\u51bb\u6548\u679c\u4e91",
      "color": 3138042,
      "weight": 10,
      "affixType": ["SUFFIX"]
    },
    "Heart Frag Change": {
      "tags": [
        "focusHitHearts"
      ],
      "display": "\u7ea2\u5fc3\u788e\u7247\u6982\u7387",
      "color": 2293541,
      "weight": 10,
      "affixType": ["PREFIX"]
    },
    "Poison Cloud": {
      "tags": [
        "focusPoisonCloud"
      ],
      "display": "\u5267\u6bd2\u6548\u679c\u4e91",
      "color": 4236591,
      "weight": 10,
      "affixType": ["SUFFIX"]
    },
    "Healing Cloud": {
      "tags": [
        "focusHealingCloud"
      ],
      "display": "\u751f\u547d\u6062\u590d\u6548\u679c\u4e91",
      "color": 16150747,
      "weight": 10,
      "affixType": ["SUFFIX"]
    },
    "Fear Cloud": {
      "tags": [
        "focusFearCloud"
      ],
      "display": "\u6050\u60e7\u6548\u679c\u4e91",
      "color": 2818160,
      "weight": 10,
      "affixType": ["SUFFIX"]
    },
    "Health": {
      "tags": [
        "focusHealth"
      ],
      "display": "\u751f\u547d\u503c",
      "color": 2293541,
      "weight": 10,
      "affixType": ["PREFIX"]
    },
    "HealingEff": {
      "tags": [
        "focusHealingEff"
      ],
      "display": "\u6cbb\u7597\u6548\u7387",
      "color": 9371426,
      "weight": 10,
      "affixType": ["SUFFIX"]
    },
    "Armor": {
      "tags": [
        "focusArmor"
      ],
      "display": "\u62a4\u7532\u503c",
      "color": 4766456,
      "weight": 10,
      "affixType": ["PREFIX"]
    },
    "ManaRegen": {
      "tags": [
        "focusManaRegen"
      ],
      "display": "\u9b54\u529b\u518d\u751f",
      "color": 65535,
      "weight": 10,
      "affixType": ["SUFFIX"]
    },
    "Trap Disarming": {
      "tags": [
        "focusTrapDisarming"
      ],
      "display": "\u9677\u9631\u89e3\u9664",
      "color": 8471551,
      "weight": 10,
      "affixType": ["SUFFIX"]
    },
    "Cooldown": {
      "tags": [
        "focusCooldown"
      ],
      "display": "\u51b7\u5374",
      "color": 63668,
      "weight": 10,
      "affixType": ["SUFFIX"]
    },
    "Durability": {
      "tags": [
        "focusDurability"
      ],
      "display": "\u8010\u4e45\u5ea6",
      "color": 14668030,
      "weight": 10,
      "affixType": ["PREFIX","SUFFIX"]
    },
    "Damage": {
      "tags": [
        "focusDamage"
      ],
      "display": "\u4f24\u5bb3\u767e\u5206\u6bd4",
      "color": 16739072,
      "weight": 10,
      "affixType": ["PREFIX"]
    },
    "Soul Hunting": {
      "tags": [
        "focusSoulChance"
      ],
      "display": "\u7075\u9b42\u6570\u91cf",
      "color": 4653308,
      "weight": 10,
      "affixType": ["PREFIX","SUFFIX"]
    },
    "Chaining": {
      "tags": [
        "focusChaining"
      ],
      "display": "\u8fde\u9501",
      "color": 6119096,
      "weight": 10,
      "affixType": ["PREFIX"]
    },
    "ManaPercentile": {
      "tags": [
        "focusManaPercentile"
      ],
      "display": "\u6700\u5927\u9b54\u529b\u503c\u767e\u5206\u6bd4",
      "color": 65535,
      "weight": 10,
      "affixType": ["PREFIX"]
    },
    "MiningSpeed": {
      "tags": [
        "focusMiningSpeed"
      ],
      "display": "\u6316\u6398\u901f\u5ea6",
      "color": 4766456,
      "weight": 10,
      "affixType": ["PREFIX"]
    },
    "Copiously": {
      "tags": [
        "focusCopiously"
      ],
      "display": "\u5bcc\u8db3",
      "color": 16205696,
      "weight": 10,
      "affixType": ["SUFFIX"]
    },
    "MagnetRange": {
      "tags": [
        "focusMagnetRange"
      ],
      "display": "\u62fe\u53d6\u8303\u56f4",
      "color": 16364415,
      "weight": 10,
      "affixType": ["PREFIX"]
    },
    "MagnetVelocity": {
      "tags": [
        "focusMagnetVelocity"
      ],
      "display": "\u5438\u5f15\u901f\u5ea6",
      "color": 14608287,
      "weight": 10,
      "affixType": ["PREFIX"]
    },
    "AttackDamage": {
      "tags": [
        "focusAttackDamage"
      ],
      "display": "\u653b\u51fb\u4f24\u5bb3",
      "color": 13116966,
      "weight": 10,
      "affixType": ["PREFIX"]
    },
    "Stunning": {
      "tags": [
        "focusStun"
      ],
      "display": "\u7729\u6655\u653b\u51fb",
      "color": 1681124,
      "weight": 10,
      "affixType": ["SUFFIX"]
    },
    "Shocking": {
      "tags": [
        "focusShocking"
      ],
      "display": "\u9707\u51fb",
      "color": 13819995,
      "weight": 10,
      "affixType": ["SUFFIX"]
    },
    "Block": {
      "tags": [
        "focusBlock"
      ],
      "display": "\u683c\u6321\u6982\u7387",
      "color": 16109454,
      "weight": 0,
      "affixType": ["PREFIX"]
    },
    "ThornsDamage": {
      "tags": [
        "focusThornsDamage"
      ],
      "display": "\u8346\u68d8\u4f24\u5bb3",
      "color": 15507136,
      "weight": 10,
      "affixType": ["PREFIX"]
    },
    "Sweeping": {
      "tags": [
        "focusSweeping"
      ],
      "display": "\u6a2a\u626b\u653b\u51fb",
      "color": 14727777,
      "weight": 0,
      "affixType": ["SUFFIX"]
    },
    "DamageIllagers": {
      "tags": [
        "focusDamageIllager"
      ],
      "display": "\u707e\u5384\u4f24\u5bb3",
      "color": 40882,
      "weight": 0,
      "affixType": ["PREFIX"]
    },
    "DamageSpiders": {
      "tags": [
        "focusDamageSpiders"
      ],
      "display": "\u8282\u80a2\u4f24\u5bb3",
      "color": 8281694,
      "weight": 0,
      "affixType": ["PREFIX"]
    },
    "DamageUndead": {
      "tags": [
        "focusDamageUndead"
      ],
      "display": "\u4ea1\u7075\u4f24\u5bb3",
      "color": 16382128,
      "weight": 0,
      "affixType": ["PREFIX"]
    },
    "DamageNether": {
      "tags": [
        "focusDamageNether"
      ],
      "display": "\u4e0b\u754c\u4f24\u5bb3",
      "color": 16757889,
      "weight": 0,
      "affixType": ["PREFIX"]
    },
    "DamageChampion": {
      "tags": [
        "focusDamageChampion"
      ],
      "display": "\u51a0\u519b\u4f24\u5bb3",
      "color": 6213132,
      "weight": 10,
      "affixType": ["PREFIX"]
    },
    "DamageDungeon": {
      "tags": [
        "focusDamageDungeon"
      ],
      "display": "\u5730\u7262\u4f24\u5bb3",
      "color": 823502,
      "weight": 10,
      "affixType": ["PREFIX"]
    },
    "DamageTank": {
      "tags": [
        "focusDamageTank"
      ],
      "display": "\u5766\u514b\u4f24\u5bb3",
      "color": 13513996,
      "weight": 10,
      "affixType": ["PREFIX"]
    },
    "DamageHorde": {
      "tags": [
        "focusDamageHorde"
      ],
      "display": "\u96c6\u7fa4\u4f24\u5bb3",
      "color": 13094412,
      "weight": 10,
      "affixType": ["PREFIX"]
    },
    "DamageAssassin": {
      "tags": [
        "focusDamageAssassin"
      ],
      "display": "\u523a\u5ba2\u4f24\u5bb3",
      "color": 11881191,
      "weight": 10,
      "affixType": ["PREFIX"]
    },
    "DamageDweller": {
      "tags": [
        "focusDamageDweller"
      ],
      "display": "\u5c45\u6c11\u4f24\u5bb3",
      "color": 15895195,
      "weight": 10,
      "affixType": ["PREFIX"]
    },
    "ItemQuantity": {
      "tags": [
        "focusItemQuantity"
      ],
      "display": "\u7269\u54c1\u6570\u91cf",
      "color": 15239698,
      "weight": 10,
      "affixType": ["SUFFIX"]
    },
    "ItemRarity": {
      "tags": [
        "focusItemRarity"
      ],
      "display": "\u7269\u54c1\u7a00\u6709\u5ea6",
      "color": 15054873,
      "weight": 10,
      "affixType": ["SUFFIX"]
    },
    "AOE": {
      "tags": [
        "focusEffectRadius"
      ],
      "display": "\u6548\u679c\u4e91",
      "color": 15319925,
      "weight": 10,
      "affixType": ["SUFFIX"]
    },
    "Reach": {
      "tags": [
        "focusReach"
      ],
      "display": "\u89e6\u53ca\u8ddd\u79bb",
      "color": 8706047,
      "weight": 5,
      "affixType": ["PREFIX"]
    },
    "AbilityDamage": {
      "tags": [
        "focusAbilityDamage"
      ],
      "display": "\u6cd5\u672f\u4f24\u5bb3\u767e\u5206\u6bd4",
      "color": 16711883,
      "weight": 10,
      "affixType": ["PREFIX"]
    }
  }
}